social_liu.py
social_auth_liu-0.0.3.dist-info/DESCRIPTION.rst
social_auth_liu-0.0.3.dist-info/METADATA
social_auth_liu-0.0.3.dist-info/RECORD
social_auth_liu-0.0.3.dist-info/WHEEL
social_auth_liu-0.0.3.dist-info/metadata.json
social_auth_liu-0.0.3.dist-info/top_level.txt
