Metadata-Version: 2.0
Name: social-auth-liu
Version: 0.0.3
Summary: UNKNOWN
Home-page: https://github.com/ovidner/python-social-auth-liu
Author: Olle Vidner
Author-email: olle@vidner.se
License: MIT
Platform: UNKNOWN
Requires-Dist: social-auth-core (==1.*)
Requires-Dist: PyJWT (==1.*)
Requires-Dist: cryptography (==1.*)
